{
  "version": "1.0.0",
  "exportedAt": "2025-12-08T08:00:21.545Z",
  "fundName": "Quỹ Đầu Tư Cá Nhân",
  "fundId": "cmiswvlwf0000kz044h7xdmp6",
  "stats": {
    "totalAccounts": 3,
    "totalTransactions": 10,
    "totalAssetHoldings": 2,
    "totalFees": 0
  },
  "data": {
    "fund": {
      "id": "cmiswvlwf0000kz044h7xdmp6",
      "name": "Quỹ Đầu Tư Cá Nhân",
      "description": "Quỹ đầu tư cá nhân",
      "initialVnd": 0,
      "initialCapital": 700000000,
      "additionalCapital": 0,
      "withdrawnCapital": 0,
      "retainedEarnings": 0,
      "earnInterestMethod": "reduce_avg_price",
      "createdAt": "2025-12-05T13:39:27.519Z",
      "updatedAt": "2025-12-05T23:21:12.481Z"
    },
    "accounts": [
      {
        "id": "cmiswvm6f0002kz042vigahpz",
        "fundId": "cmiswvlwf0000kz044h7xdmp6",
        "name": "Binance Spot tranhuuhanh1902@gmail.com",
        "type": "cex",
        "platform": "Binance",
        "isActive": true,
        "createdAt": "2025-12-05T13:39:27.879Z",
        "updatedAt": "2025-12-05T23:21:38.608Z"
      },
      {
        "id": "cmiswvmgf0004kz0463fuq7ui",
        "fundId": "cmiswvlwf0000kz044h7xdmp6",
        "name": "Binance Earn tranhuuhanh1902@gmail.com",
        "type": "earn_lending",
        "platform": "Binance",
        "isActive": true,
        "createdAt": "2025-12-05T13:39:28.240Z",
        "updatedAt": "2025-12-05T23:21:31.046Z"
      },
      {
        "id": "cmiswvmlg0006kz04z0tgk8yk",
        "fundId": "cmiswvlwf0000kz044h7xdmp6",
        "name": "Ví lạnh 1",
        "type": "cold_wallet",
        "platform": "trust_wallet",
        "isActive": true,
        "createdAt": "2025-12-05T13:39:28.420Z",
        "updatedAt": "2025-12-05T13:39:28.420Z"
      }
    ],
    "transactions": [
      {
        "id": "cmiswwwmf0005lb045f4inbmh",
        "fundId": "cmiswvlwf0000kz044h7xdmp6",
        "accountId": null,
        "type": "capital_in",
        "amount": 700000000,
        "currency": "VND",
        "price": null,
        "fee": null,
        "feeCurrency": null,
        "fromLocation": null,
        "toLocation": null,
        "note": "Nạp 700tr",
        "costBasis": 0,
        "realizedPnL": 0,
        "createdAt": "2025-12-05T13:40:27.021Z"
      },
      {
        "id": "cmisx0rqw0009lb04a36njy68",
        "fundId": "cmiswvlwf0000kz044h7xdmp6",
        "accountId": "cmiswvmgf0004kz0463fuq7ui",
        "type": "buy_usdt",
        "amount": 3632.46,
        "currency": "USDT",
        "price": 27529.55297512,
        "fee": null,
        "feeCurrency": null,
        "fromLocation": null,
        "toLocation": "cmiswvmgf0004kz0463fuq7ui",
        "note": null,
        "costBasis": 0,
        "realizedPnL": 0,
        "createdAt": "2025-12-05T13:43:28.201Z"
      },
      {
        "id": "cmisxj8kh0001k304hqxdg88z",
        "fundId": "cmiswvlwf0000kz044h7xdmp6",
        "accountId": "cmiswvmgf0004kz0463fuq7ui",
        "type": "buy_usdt",
        "amount": 3591.51,
        "currency": "USDT",
        "price": 27843.44,
        "fee": null,
        "feeCurrency": null,
        "fromLocation": null,
        "toLocation": "cmiswvmgf0004kz0463fuq7ui",
        "note": "Mua USDT Ngày 26/11/2025",
        "costBasis": 0,
        "realizedPnL": 0,
        "createdAt": "2025-12-05T13:57:49.813Z"
      },
      {
        "id": "cmisxjab50005k30414671bxt",
        "fundId": "cmiswvlwf0000kz044h7xdmp6",
        "accountId": "cmiswvmgf0004kz0463fuq7ui",
        "type": "buy_usdt",
        "amount": 3588.29,
        "currency": "USDT",
        "price": 27868.43,
        "fee": null,
        "feeCurrency": null,
        "fromLocation": null,
        "toLocation": "cmiswvmgf0004kz0463fuq7ui",
        "note": "Mua USDT Ngày 18/11/2025",
        "costBasis": 0,
        "realizedPnL": 0,
        "createdAt": "2025-12-05T13:57:51.183Z"
      },
      {
        "id": "cmisxlc8y000hk3040kk29tz2",
        "fundId": "cmiswvlwf0000kz044h7xdmp6",
        "accountId": "cmiswvmgf0004kz0463fuq7ui",
        "type": "buy_usdt",
        "amount": 3597.84,
        "currency": "USDT",
        "price": 27794.45,
        "fee": null,
        "feeCurrency": null,
        "fromLocation": null,
        "toLocation": "cmiswvmgf0004kz0463fuq7ui",
        "note": "Mua USDT ngày 16/11/2025",
        "costBasis": 0,
        "realizedPnL": 0,
        "createdAt": "2025-12-05T13:59:27.894Z"
      },
      {
        "id": "cmisxm8470001jp04wamishl9",
        "fundId": "cmiswvlwf0000kz044h7xdmp6",
        "accountId": "cmiswvmgf0004kz0463fuq7ui",
        "type": "buy_usdt",
        "amount": 3574.31,
        "currency": "USDT",
        "price": 27977.43,
        "fee": null,
        "feeCurrency": null,
        "fromLocation": null,
        "toLocation": "cmiswvmgf0004kz0463fuq7ui",
        "note": "Mua USDT 04/11/2025",
        "costBasis": 0,
        "realizedPnL": 0,
        "createdAt": "2025-12-05T14:00:09.190Z"
      },
      {
        "id": "cmisxn6j50007jp04k1v4ushh",
        "fundId": "cmiswvlwf0000kz044h7xdmp6",
        "accountId": "cmiswvmgf0004kz0463fuq7ui",
        "type": "buy_usdt",
        "amount": 3580.97,
        "currency": "USDT",
        "price": 27925.39,
        "fee": null,
        "feeCurrency": null,
        "fromLocation": null,
        "toLocation": "cmiswvmgf0004kz0463fuq7ui",
        "note": "Mua USDT 04/11/2025 lần 2",
        "costBasis": 0,
        "realizedPnL": 0,
        "createdAt": "2025-12-05T14:00:53.791Z"
      },
      {
        "id": "cmisxo418000nk304qocjl2k0",
        "fundId": "cmiswvlwf0000kz044h7xdmp6",
        "accountId": "cmiswvmgf0004kz0463fuq7ui",
        "type": "buy_usdt",
        "amount": 1794.83,
        "currency": "USDT",
        "price": 27857.79,
        "fee": null,
        "feeCurrency": null,
        "fromLocation": null,
        "toLocation": "cmiswvmgf0004kz0463fuq7ui",
        "note": "Mua USDT 24/10/2025 lần 1",
        "costBasis": 0,
        "realizedPnL": 0,
        "createdAt": "2025-12-05T14:01:37.215Z"
      },
      {
        "id": "cmisxopk0000tk304zvfq77qu",
        "fundId": "cmiswvlwf0000kz044h7xdmp6",
        "accountId": "cmiswvmgf0004kz0463fuq7ui",
        "type": "buy_usdt",
        "amount": 1794.83,
        "currency": "USDT",
        "price": 27857.79,
        "fee": null,
        "feeCurrency": null,
        "fromLocation": null,
        "toLocation": "cmiswvmgf0004kz0463fuq7ui",
        "note": "Mua USDT 24/10/2025 lần 2",
        "costBasis": 0,
        "realizedPnL": 0,
        "createdAt": "2025-12-05T14:02:04.211Z"
      },
      {
        "id": "cmisycgel000zk3048enzwysa",
        "fundId": "cmiswvlwf0000kz044h7xdmp6",
        "accountId": "cmiswvmgf0004kz0463fuq7ui",
        "type": "earn_interest",
        "amount": 29.81,
        "currency": "USDT",
        "price": null,
        "fee": null,
        "feeCurrency": null,
        "fromLocation": null,
        "toLocation": "cmiswvmgf0004kz0463fuq7ui",
        "note": "Lãi earn",
        "costBasis": 0,
        "realizedPnL": 0,
        "createdAt": "2025-12-05T14:20:32.993Z"
      }
    ],
    "assetHoldings": [
      {
        "id": "cmithnqbs0017kz04a2qj4o88",
        "fundId": "cmiswvlwf0000kz044h7xdmp6",
        "accountId": null,
        "asset": "VND",
        "amount": 28.02989558875561,
        "avgPrice": 1,
        "location": null,
        "createdAt": "2025-12-05T23:21:11.945Z",
        "updatedAt": "2025-12-05T23:21:11.945Z"
      },
      {
        "id": "cmithnqlp0019kz04vmr86iwy",
        "fundId": "cmiswvlwf0000kz044h7xdmp6",
        "accountId": "cmiswvmgf0004kz0463fuq7ui",
        "asset": "USDT",
        "amount": 25184.85,
        "avgPrice": 27794.48644602229,
        "location": null,
        "createdAt": "2025-12-05T23:21:12.124Z",
        "updatedAt": "2025-12-05T23:21:12.124Z"
      }
    ],
    "fees": []
  }
}